LICENSE
MANIFEST.in
README.md
setup.py
facebook/__init__.py
python_fb.egg-info/PKG-INFO
python_fb.egg-info/SOURCES.txt
python_fb.egg-info/dependency_links.txt
python_fb.egg-info/not-zip-safe
python_fb.egg-info/top_level.txt