Metadata-Version: 1.0
Name: python-fb
Version: 0.2
Summary: This client library is designed to support the Facebook Graph API and the official Facebook JavaScript SDK, which is the canonical way to implement Facebook authentication.
Home-page: https://github.com/aino/python-fb
Author: Mikko Hellsing
Author-email: mikko@aino.se
License: UNKNOWN
Platform: UNKNOWN
